fasteda/__init__.py
fasteda/advanced_stats.py
fasteda/alerts.py
fasteda/analysis.py
fasteda/cli.py
fasteda/display.py
fasteda/html_report.py
fasteda/interactive.py
fasteda/loader.py
fasteda/plugins.py
fasteda/presets.py
fasteda/report.py
fasteda/visualize.py
speedyeda-0.2.0.dist-info/METADATA
speedyeda-0.2.0.dist-info/WHEEL
speedyeda-0.2.0.dist-info/entry_points.txt
speedyeda-0.2.0.dist-info/licenses/LICENSE
speedyeda-0.2.0.dist-info/RECORD
