Metadata-Version: 2.4
Name: speedyeda
Version: 0.2.0
Summary: 🚀 One-line data exploration for developers & data scientists
Project-URL: Homepage, https://github.com/Dawaman43/fasteda
Project-URL: Documentation, https://github.com/Dawaman43/fasteda#readme
Project-URL: Repository, https://github.com/Dawaman43/fasteda
Project-URL: Issues, https://github.com/Dawaman43/fasteda/issues
Author-email: Dawit Worku <dawitworkujima@gmail.com>
License: MIT
License-File: LICENSE
Keywords: analysis,cli,data,eda,exploratory,visualization
Classifier: Development Status :: 3 - Alpha
Classifier: Intended Audience :: Developers
Classifier: Intended Audience :: Science/Research
Classifier: License :: OSI Approved :: MIT License
Classifier: Programming Language :: Python :: 3
Classifier: Programming Language :: Python :: 3.10
Classifier: Programming Language :: Python :: 3.11
Classifier: Programming Language :: Python :: 3.12
Classifier: Topic :: Scientific/Engineering :: Information Analysis
Requires-Python: >=3.10
Requires-Dist: matplotlib>=3.7.0
Requires-Dist: numpy>=1.24.0
Requires-Dist: openpyxl>=3.1.0
Requires-Dist: pandas>=2.0.0
Requires-Dist: plotly>=5.0.0
Requires-Dist: rich>=13.0.0
Requires-Dist: scipy>=1.10.0
Requires-Dist: seaborn>=0.12.0
Requires-Dist: tabulate>=0.9.0
Provides-Extra: dev
Requires-Dist: black>=23.0.0; extra == 'dev'
Requires-Dist: pytest>=7.0.0; extra == 'dev'
Requires-Dist: ruff>=0.1.0; extra == 'dev'
